[
    {
        "id": "1",
        "name": "Anant Vijay",
        "ratings": "★★☆☆☆",
        "img": "https://images.pexels.com/photos/220453/pexels-photo-220453.jpeg?auto=compress&cs=tinysrgb&w=1260&h=750&dpr=1",
        "review": "This was different. Full disclosure-I'm an unapologetic John Grisham fan! I've randomly read many Grisham books. Recently, I decided to read the complete library in the order written."
    },
    {
        "id": "2",
        "name": "Vasdev Mohi",
        "ratings": "★★★★☆",
        "img": "https://images.unsplash.com/photo-1564564321837-a57b7070ac4f?ixlib=rb-1.2.1&ixid=MnwxMjA3fDB8MHxzZWFyY2h8Nnx8bWFufGVufDB8fDB8fA%3D%3D&w=1000&q=80",
        "review": "This book became a pretty good movie. I read it years ago when I still bought every book this author wrote. This second read left me not nearly as satisfied. The story is good, it is just not presented as coherently as I remembered it. "
    },
    {
        "id": "3",
        "name": "Richard Powers",
        "ratings": "★★★★☆",
        "img": "https://preview.redd.it/cpslext1vx971.png?auto=webp&s=a67d767ddec283c3490613cdb0b40c180a33daf6",
        "review": "Dear Mr Grisham; Please consider writing another book about Mark and his family when Mark is in his twenties! What a great story it would be! I have been reading for 66 years and your book is on the very TOP of my list! Thanks, Collette Bills, Lincoln, Nebraska "
    }
]